{
  "parent": "bingo:item_detection/root",
  "criteria": {
    "has_obtained_item": {
      "trigger": "minecraft:inventory_changed",
      "conditions": {
        "items": [
          {
            "items": "minecraft:tropical_fish_bucket",
            "count": {
              "min": 1,
              "max": 64
            }
          }
        ]
      }
    }
  },
  "display": {
    "description": "Category 40, Difficulty 2",
    "frame": "task",
    "show_toast": false,
    "announce_to_chat": false,
    "hidden": true,
    "icon": {
      "count": 1,
      "id": "minecraft:tropical_fish_bucket"
    },
    "title": "Bucket of Tropical Fish"
  },
  "rewards": {
    "function": "bingo:advancement/tropical_fish_bucket"
  }
}